luxlib/__init__.py
luxlib/luxlib.py
luxlib-0.0.5.dist-info/LICENSE
luxlib-0.0.5.dist-info/METADATA
luxlib-0.0.5.dist-info/WHEEL
luxlib-0.0.5.dist-info/top_level.txt
luxlib-0.0.5.dist-info/RECORD
