Metadata-Version: 2.1
Name: luxlib
Version: 0.0.5
Summary: LuxLIB est une librairie Python permettant la mise à jour automatique depuis un serveur. Mais aussi de pouvoir mettre à jour son serveur depuis le client.
Home-page: https://github.com/TheAngelLCF/LuxLIB
Author: Valentin Thuillier
Author-email: valentinrthuillier@gmail.com
Classifier: Programming Language :: Python :: 3
Classifier: Operating System :: OS Independent
Classifier: License :: OSI Approved :: MIT License
License-File: LICENSE
